odoo/addons/sms_alternative_provider/README.rst
odoo/addons/sms_alternative_provider/__init__.py
odoo/addons/sms_alternative_provider/__manifest__.py
odoo/addons/sms_alternative_provider/data/ir_sms_gateway.xml
odoo/addons/sms_alternative_provider/i18n/sms_alternative_provider.pot
odoo/addons/sms_alternative_provider/models/__init__.py
odoo/addons/sms_alternative_provider/models/ir_sms_gateway.py
odoo/addons/sms_alternative_provider/models/sms_api.py
odoo/addons/sms_alternative_provider/models/sms_sms.py
odoo/addons/sms_alternative_provider/readme/CONFIGURE.md
odoo/addons/sms_alternative_provider/readme/CONTRIBUTORS.md
odoo/addons/sms_alternative_provider/readme/DESCRIPTION.md
odoo/addons/sms_alternative_provider/readme/USAGE.md
odoo/addons/sms_alternative_provider/security/ir.model.access.csv
odoo/addons/sms_alternative_provider/static/description/icon.png
odoo/addons/sms_alternative_provider/static/description/index.html
odoo/addons/sms_alternative_provider/tests/__init__.py
odoo/addons/sms_alternative_provider/tests/test_sms_alternative_provider.py
odoo/addons/sms_alternative_provider/views/ir_sms_gateway.xml
odoo/addons/sms_alternative_provider/views/sms_sms.xml
odoo_addon_sms_alternative_provider-16.0.1.0.0.2.dist-info/METADATA
odoo_addon_sms_alternative_provider-16.0.1.0.0.2.dist-info/WHEEL
odoo_addon_sms_alternative_provider-16.0.1.0.0.2.dist-info/top_level.txt
odoo_addon_sms_alternative_provider-16.0.1.0.0.2.dist-info/RECORD
